{
  "generator-jhipster": {
    "applicationType": "monolith",
    "authenticationType": "jwt",
    "baseName": "agentType",
    "buildTool": "maven",
    "cacheProvider": "ehcache",
    "clientFramework": "angular",
    "clientTestFrameworks": [],
    "clientTheme": "darkly",
    "clientThemeVariant": "primary",
    "creationTimestamp": 1742899655370,
    "databaseType": "sql",
    "devDatabaseType": "mysql",
    "enableHibernateCache": false,
    "enableTranslation": true,
    "entities": [],
    "feignClient": null,
    "jhipsterVersion": "8.8.0",
    "jwtSecretKey": "YzAxOWY3ZjEyNTY4YzEwYzk5ZTBjMDk2MTcxOGU0ZDQ4ZTdkOTZlY2I3Y2JhNmUxNDgzYzQ2NWJmNWI1NjQxNDlmOTEwZTlhYTVlMDYxNDQ4Mjk1OWQ3YjFmNzVlNmU4NDVjMjhkOGRhODRiMDExZWE0NzkwNzBhNjJkNDVmMjM=",
    "languages": ["en"],
    "microfrontend": null,
    "microfrontends": [],
    "nativeLanguage": "en",
    "packageName": "com.bpl",
    "prodDatabaseType": "mysql",
    "reactive": false,
    "serverPort": null,
    "serviceDiscoveryType": null,
    "syncUserWithIdp": null,
    "testFrameworks": [],
    "withAdminUi": true
  }
}
